django_source_revision-0.1.0.dist-info/DESCRIPTION.rst
django_source_revision-0.1.0.dist-info/METADATA
django_source_revision-0.1.0.dist-info/RECORD
django_source_revision-0.1.0.dist-info/WHEEL
django_source_revision-0.1.0.dist-info/metadata.json
django_source_revision-0.1.0.dist-info/top_level.txt
sourcerevision/__init__.py
sourcerevision/context_processors.py
sourcerevision/loader.py
sourcerevision/middleware.py
sourcerevision/templatetags/__init__.py
sourcerevision/templatetags/staticfiles.py
