Metadata-Version: 2.0
Name: django-source-revision
Version: 0.1.0
Summary: Django Source Revision
Home-page: https://github.com/dobarkod/django-source-revision
Author: Senko Rasic
Author-email: senko.rasic@goodcode.io
License: MIT
Platform: UNKNOWN
Classifier: Development Status :: 4 - Beta
Classifier: Environment :: Web Environment
Classifier: Framework :: Django
Classifier: Intended Audience :: Developers
Classifier: License :: OSI Approved :: MIT License
Classifier: Programming Language :: Python
Classifier: Programming Language :: Python :: 3
Classifier: Topic :: Software Development :: Libraries :: Python Modules
Requires-Dist: Django (>=1.4)
